qual_qualis/__init__.py
qual_qualis/cli/__init__.py
qual_qualis/cli/file_handler/__init__.py
qual_qualis/cli/file_handler/bib_handler.py
qual_qualis/cli/file_handler/csv_handler.py
qual_qualis/cli/file_handler/file_handler.py
qual_qualis/data/__init__.py
qual_qualis/data/conferences.csv
qual_qualis/data/journals.csv
qual_qualis/data/model.py
qual_qualis/data/service.py
qual_qualis/index/create.sql
qual_qualis/index/index.py
qual_qualis/index/model.py
qual_qualis/index/search.py
qual_qualis-1.0.1.dist-info/LICENSE
qual_qualis-1.0.1.dist-info/METADATA
qual_qualis-1.0.1.dist-info/WHEEL
qual_qualis-1.0.1.dist-info/entry_points.txt
qual_qualis-1.0.1.dist-info/top_level.txt
qual_qualis-1.0.1.dist-info/RECORD
